mqtt_mcp/__init__.py
mqtt_mcp/cache.py
mqtt_mcp/mqtt_client.py
mqtt_mcp/server.py
mqtt_mcp/tools/__init__.py
mqtt_mcp/tools/publish.py
mqtt_mcp/tools/record.py
mqtt_mcp/tools/topics.py
mqtt_mcp/tools/value.py
mqtt_mcp_server-1.0.7.dist-info/METADATA
mqtt_mcp_server-1.0.7.dist-info/WHEEL
mqtt_mcp_server-1.0.7.dist-info/entry_points.txt
mqtt_mcp_server-1.0.7.dist-info/RECORD
