Metadata-Version: 2.4
Name: mqtt-mcp-server
Version: 1.0.7
Summary: MQTT Model Context Protocol Server for AI-powered smart home control
Project-URL: Homepage, https://github.com/yourusername/mqtt-mcp-server
Project-URL: Issues, https://github.com/yourusername/mqtt-mcp-server/issues
Author: MQTT MCP Server Contributors
License-Expression: MIT
Requires-Python: >=3.10
Requires-Dist: aiomqtt>=2.0.0
Requires-Dist: mcp>=1.0.0
Requires-Dist: pydantic>=2.0.0
